explorer/__init__.py
explorer/__init__.pyc
explorer/actions.py
explorer/actions.pyc
explorer/admin.py
explorer/admin.pyc
explorer/app_settings.py
explorer/app_settings.pyc
explorer/constants.py
explorer/constants.pyc
explorer/counter.py
explorer/forms.py
explorer/forms.pyc
explorer/models.py
explorer/models.pyc
explorer/tasks.py
explorer/tasks.pyc
explorer/urls.py
explorer/urls.pyc
explorer/utils.py
explorer/utils.pyc
explorer/views.py
explorer/views.pyc
explorer/__pycache__/__init__.cpython-311.pyc
explorer/__pycache__/models.cpython-311.pyc
explorer/__pycache__/utils.cpython-311.pyc
explorer/migrations/0001_initial.py
explorer/migrations/0001_initial.pyc
explorer/migrations/0002_auto_20150501_1515.py
explorer/migrations/0002_auto_20150501_1515.pyc
explorer/migrations/0003_query_snapshot.py
explorer/migrations/0003_query_snapshot.pyc
explorer/migrations/0004_querylog_duration.py
explorer/migrations/0004_querylog_duration.pyc
explorer/migrations/0005_querychangelog.py
explorer/migrations/0005_querychangelog.pyc
explorer/migrations/0006_auto_20230207_0103.py
explorer/migrations/0006_auto_20230207_0103.pyc
explorer/migrations/__init__.py
explorer/migrations/__init__.pyc
explorer/static/explorer/explorer.css
explorer/static/explorer/explorer.js
explorer/static/explorer/query-list.js
explorer/templates/explorer/base.html
explorer/templates/explorer/params.html
explorer/templates/explorer/play.html
explorer/templates/explorer/preview_pane.html
explorer/templates/explorer/query.html
explorer/templates/explorer/query_confirm_delete.html
explorer/templates/explorer/query_list.html
explorer/templates/explorer/querychangelog_list.html
explorer/templates/explorer/querylog_list.html
explorer/templates/explorer/schema.html
explorer/tests/__init__.py
explorer/tests/__init__.pyc
explorer/tests/factories.py
explorer/tests/factories.pyc
explorer/tests/settings.py
explorer/tests/settings.pyc
explorer/tests/test_actions.py
explorer/tests/test_actions.pyc
explorer/tests/test_forms.py
mayank_django_sql_explorer-2.0.0.dist-info/AUTHORS
mayank_django_sql_explorer-2.0.0.dist-info/LICENSE
mayank_django_sql_explorer-2.0.0.dist-info/METADATA
mayank_django_sql_explorer-2.0.0.dist-info/WHEEL
mayank_django_sql_explorer-2.0.0.dist-info/top_level.txt
mayank_django_sql_explorer-2.0.0.dist-info/RECORD
