Metadata-Version: 2.1
Name: mayank-django-sql-explorer
Version: 2.0.0
Summary: A pluggable app that allows users (admins) to execute SQL, view, and export the results. Inspired by Stack Exchange Data Explorer.
Home-page: https://github.com/epantry/django-sql-explorer
Author: Chris Clark
Author-email: chris@untrod.com
License: MIT
Keywords: django sql explorer reports reporting csv database query
Classifier: Development Status :: 5 - Production/Stable
Classifier: Intended Audience :: Developers
Classifier: License :: OSI Approved :: MIT License
Classifier: Topic :: Utilities
Classifier: Framework :: Django :: 1.7
Classifier: Framework :: Django :: 1.8
Classifier: Framework :: Django :: 1.9
Classifier: Programming Language :: Python :: 2
Classifier: Programming Language :: Python :: 2.7
Classifier: Programming Language :: Python :: 3
Classifier: Programming Language :: Python :: 3.4
License-File: LICENSE
License-File: AUTHORS
Requires-Dist: Django (>=1.6.7)
Requires-Dist: sqlparse (>=0.1.11)
Requires-Dist: unicodecsv (>=0.13.0)
Requires-Dist: six (>=1.10.0)
Requires-Dist: ago (==0.0.93)
Requires-Dist: future (==0.18.2)
